[
  {
    "symbol": "AMN",
    "date": "2025-12-31",
    "fiscalYear": "2025",
    "period": "FY",
    "reportedCurrency": "USD",
    "marketCap": 607090960,
    "enterpriseValue": 1406460960,
    "evToSales": 0.5151062195720892,
    "evToOperatingCashFlow": 5.219611886126543,
    "evToFreeCashFlow": 5.219611886126543,
    "evToEBITDA": 13.907730401075865,
    "netDebtToEBITDA": 7.904536824618305,
    "currentRatio": 0.9441876408812806,
    "incomeQuality": 0,
    "grahamNumber": null,
    "grahamNetNet": -29.363438124659275,
    "taxBurden": 0.9469538802529115,
    "interestBurden": 1.8218740986443611,
    "workingCapital": -32238000,
    "investedCapital": 1143458000,
    "returnOnAssets": -0.045700625612731346,
    "operatingReturnOnAssets": 0.01470874537732431,
    "returnOnTangibleAssets": -0.09073240472822562,
    "returnOnEquity": -0.14904392732664076,
    "returnOnInvestedCapital": 0.020628951125416135,
    "returnOnCapitalEmployed": 0.021870855981531073,
    "earningsYield": -0.15764029825118794,
    "freeCashFlowYield": 0.44384946861999064,
    "capexToOperatingCashFlow": 0,
    "capexToDepreciation": 0,
    "capexToRevenue": 0,
    "salesGeneralAndAdministrativeToRevenue": 0,
    "researchAndDevelopementToRevenue": 0,
    "stockBasedCompensationToRevenue": 0,
    "intangiblesToTotalAssets": 0.49631418069850297,
    "averageReceivables": 451270500,
    "averagePayables": 92932000,
    "averageInventory": 0,
    "daysOfSalesOutstanding": 51.14009556739985,
    "daysOfPayablesOutstanding": 14.734500349168584,
    "daysOfInventoryOutstanding": 0,
    "operatingCycle": 51.14009556739985,
    "cashConversionCycle": 36.40559521823126,
    "freeCashFlowToEquity": -529913000,
    "freeCashFlowToFirm": 185438574.3546105,
    "tangibleAssetValue": -397229000,
    "netCurrentAssetValue": -906625000
  },
  {
    "symbol": "AMN",
    "date": "2024-12-31",
    "fiscalYear": "2024",
    "period": "FY",
    "reportedCurrency": "USD",
    "marketCap": 913456960.0000001,
    "enterpriseValue": 2000604960,
    "evToSales": 0.670493229898575,
    "evToOperatingCashFlow": 6.243734621650469,
    "evToFreeCashFlow": 8.352315020853599,
    "evToEBITDA": 28.13552949118218,
    "netDebtToEBITDA": 15.289117655331477,
    "currentRatio": 1.0900171312879614,
    "incomeQuality": -2.1800257179597087,
    "grahamNumber": null,
    "grahamNetNet": -34.263963810621135,
    "taxBurden": 0.8516868126137194,
    "interestBurden": 1.6808118979673332,
    "workingCapital": 49130000,
    "investedCapital": 1546335000,
    "returnOnAssets": -0.06084255381506271,
    "operatingReturnOnAssets": -0.03845343579293428,
    "returnOnTangibleAssets": -0.12927970361691854,
    "returnOnEquity": -0.20800288698310265,
    "returnOnInvestedCapital": -0.04660907335984611,
    "returnOnCapitalEmployed": -0.05490705059301305,
    "earningsYield": -0.1609041328011776,
    "freeCashFlowYield": 0.2622203458825252,
    "capexToOperatingCashFlow": 0.25245460617068954,
    "capexToDepreciation": 0.4654820202671209,
    "capexToRevenue": 0.027110233626395502,
    "salesGeneralAndAdministrativeToRevenue": 0.21197567783962698,
    "researchAndDevelopementToRevenue": 0,
    "stockBasedCompensationToRevenue": 0.00781458156614041,
    "intangiblesToTotalAssets": 0.5293727312730288,
    "averageReceivables": 633261000,
    "averagePayables": 139015000,
    "averageInventory": 0,
    "daysOfSalesOutstanding": 63.608242360950754,
    "daysOfPayablesOutstanding": 17.843124290049676,
    "daysOfInventoryOutstanding": 0,
    "operatingCycle": 63.608242360950754,
    "cashConversionCycle": 45.76511807090108,
    "freeCashFlowToEquity": -847621000,
    "freeCashFlowToFirm": 141876759.8885116,
    "tangibleAssetValue": -572200000,
    "netCurrentAssetValue": -1114192000
  },
  {
    "symbol": "AMN",
    "date": "2023-12-31",
    "fiscalYear": "2023",
    "period": "FY",
    "reportedCurrency": "USD",
    "marketCap": 2933274240,
    "enterpriseValue": 4250623240,
    "evToSales": 1.1217572746508944,
    "evToOperatingCashFlow": 11.42134064191958,
    "evToFreeCashFlow": 15.933185045243611,
    "evToEBITDA": 8.512210206746289,
    "netDebtToEBITDA": 2.6380958674773107,
    "currentRatio": 1.28281978476531,
    "incomeQuality": 1.766502593993706,
    "grahamNumber": 50.67368030461599,
    "grahamNetNet": -38.29926862890256,
    "taxBurden": 0.7410733443784318,
    "interestBurden": 0.8400255297270623,
    "workingCapital": 185564000,
    "investedCapital": 1997175000,
    "returnOnAssets": 0.07204193415798282,
    "operatingReturnOnAssets": 0.11644378000411165,
    "returnOnTangibleAssets": 0.1573745192203545,
    "returnOnEquity": 0.25344659166369926,
    "returnOnInvestedCapital": 0.11018075693466771,
    "returnOnCapitalEmployed": 0.149201176401606,
    "earningsYield": 0.07182383328740514,
    "freeCashFlowYield": 0.09094887766102633,
    "capexToOperatingCashFlow": 0.28317278626415704,
    "capexToDepreciation": 0.6548745704574124,
    "capexToRevenue": 0.027812070660874145,
    "salesGeneralAndAdministrativeToRevenue": 0.1995743753255918,
    "researchAndDevelopementToRevenue": 0,
    "stockBasedCompensationToRevenue": 0.004755553467780202,
    "intangiblesToTotalAssets": 0.542226184296644,
    "averageReceivables": 849896000,
    "averagePayables": 275213500,
    "averageInventory": 0,
    "daysOfSalesOutstanding": 71.9105831913089,
    "daysOfPayablesOutstanding": 25.45426714384096,
    "daysOfInventoryOutstanding": 0,
    "operatingCycle": 71.9105831913089,
    "cashConversionCycle": 46.45631604746794,
    "freeCashFlowToEquity": -1048871000,
    "freeCashFlowToFirm": 358188710.8646483,
    "tangibleAssetValue": -754427000,
    "netCurrentAssetValue": -1251453000
  },
  {
    "symbol": "AMN",
    "date": "2022-12-31",
    "fiscalYear": "2022",
    "period": "FY",
    "reportedCurrency": "USD",
    "marketCap": 4584846620,
    "enterpriseValue": 5381277620,
    "evToSales": 1.02632638737636,
    "evToOperatingCashFlow": 8.231613854585893,
    "evToFreeCashFlow": 9.394508171107049,
    "evToEBITDA": 6.862018969360326,
    "netDebtToEBITDA": 1.0155812458875917,
    "currentRatio": 1.2747440650959923,
    "incomeQuality": 1.4722058326765004,
    "grahamNumber": 72.41592691038662,
    "grahamNetNet": -23.88945639254558,
    "taxBurden": 0.7319067154769302,
    "interestBurden": 0.9375707965217176,
    "workingCapital": 235712000,
    "investedCapital": 1813450000,
    "returnOnAssets": 0.1537382402623504,
    "operatingReturnOnAssets": 0.21497454344557052,
    "returnOnTangibleAssets": 0.3008152937868991,
    "returnOnEquity": 0.42548441311800883,
    "returnOnInvestedCapital": 0.23233539799296202,
    "returnOnCapitalEmployed": 0.3187033408884279,
    "earningsYield": 0.09685165869300116,
    "freeCashFlowYield": 0.1249356952316106,
    "capexToOperatingCashFlow": 0.12378448082015135,
    "capexToDepreciation": 0.5901933469962294,
    "capexToRevenue": 0.015433580979096521,
    "salesGeneralAndAdministrativeToRevenue": 0.17862536194209613,
    "researchAndDevelopementToRevenue": 0,
    "stockBasedCompensationToRevenue": 0.005734238473066855,
    "intangiblesToTotalAssets": 0.488928111576467,
    "averageReceivables": 991050500,
    "averagePayables": 356165000,
    "averageInventory": 0,
    "daysOfSalesOutstanding": 66.35906086348866,
    "daysOfPayablesOutstanding": 38.63833800549998,
    "daysOfInventoryOutstanding": 0,
    "operatingCycle": 66.35906086348866,
    "cashConversionCycle": 27.720722857988683,
    "freeCashFlowToEquity": -218529000,
    "freeCashFlowToFirm": 678863567.491837,
    "tangibleAssetValue": -368562000,
    "netCurrentAssetValue": -751072000
  },
  {
    "symbol": "AMN",
    "date": "2021-12-31",
    "fiscalYear": "2021",
    "period": "FY",
    "reportedCurrency": "USD",
    "marketCap": 5833306050,
    "enterpriseValue": 6519447050,
    "evToSales": 1.6363108727271358,
    "evToOperatingCashFlow": 21.35031586083129,
    "evToFreeCashFlow": 25.902377300918182,
    "evToEBITDA": 11.20767249159783,
    "netDebtToEBITDA": 1.1795545775707201,
    "currentRatio": 1.3916669245608062,
    "incomeQuality": 0.9327037032511882,
    "grahamNumber": 61.35485867156535,
    "grahamNetNet": -21.334035860333437,
    "taxBurden": 0.7374915807091802,
    "interestBurden": 0.9287089067318274,
    "workingCapital": 379678000,
    "investedCapital": 1941364000,
    "returnOnAssets": 0.10453315010092895,
    "operatingReturnOnAssets": 0.1742796759332433,
    "returnOnTangibleAssets": 0.18977859318708137,
    "returnOnEquity": 0.2817387203567559,
    "returnOnInvestedCapital": 0.16216001782779543,
    "returnOnCapitalEmployed": 0.2210379021473136,
    "earningsYield": 0.056123919642447014,
    "freeCashFlowYield": 0.04314757323593539,
    "capexToOperatingCashFlow": 0.1757391372692857,
    "capexToDepreciation": 0.5174980954125963,
    "capexToRevenue": 0.013468834042168698,
    "salesGeneralAndAdministrativeToRevenue": 0.18333532033125557,
    "researchAndDevelopementToRevenue": 0,
    "stockBasedCompensationToRevenue": 0.0063291949395555235,
    "intangiblesToTotalAssets": 0.44918366004599114,
    "averageReceivables": 739467000,
    "averagePayables": 223233500,
    "averageInventory": 19423000,
    "daysOfSalesOutstanding": 94.2540412400373,
    "daysOfPayablesOutstanding": 46.26431504273108,
    "daysOfInventoryOutstanding": 0,
    "operatingCycle": 94.2540412400373,
    "cashConversionCycle": 47.98972619730622,
    "freeCashFlowToEquity": -434448000,
    "freeCashFlowToFirm": 133653500.59582669,
    "tangibleAssetValue": -244774000,
    "netCurrentAssetValue": -620811000
  }
]
