[
  {
    "symbol": "HIMS",
    "date": "2025-12-31",
    "fiscalYear": "2025",
    "period": "FY",
    "reportedCurrency": "USD",
    "marketCap": 7304427431.96,
    "enterpriseValue": 8339568431.96,
    "evToSales": 3.552324499895001,
    "evToOperatingCashFlow": 27.798005479757073,
    "evToFreeCashFlow": 112.75629631778911,
    "evToEBITDA": 46.73964798829767,
    "netDebtToEBITDA": 5.801514353289319,
    "currentRatio": 1.8980691391114923,
    "incomeQuality": 2.33713239590231,
    "grahamNumber": 5.556232527791367,
    "grahamNetNet": -4.321267839473944,
    "taxBurden": 1.0358364804234854,
    "interestBurden": 1,
    "workingCapital": 363207000,
    "investedCapital": 1286624000,
    "returnOnAssets": 0.059574280469948324,
    "operatingReturnOnAssets": 0.08502978781683183,
    "returnOnTangibleAssets": 0.07639573305147286,
    "returnOnEquity": 0.23730514966871746,
    "returnOnInvestedCapital": 0.06933326951992375,
    "returnOnCapitalEmployed": 0.06952511435352407,
    "earningsYield": 0.017573588237504847,
    "freeCashFlowYield": 0.010125502743225148,
    "capexToOperatingCashFlow": 0.753468263968054,
    "capexToDepreciation": 4.147462478441158,
    "capexToRevenue": 0.0962861805296134,
    "salesGeneralAndAdministrativeToRevenue": 0,
    "researchAndDevelopementToRevenue": 0.06359628852331088,
    "stockBasedCompensationToRevenue": 0.05760856554910321,
    "intangiblesToTotalAssets": 0.22018837845551945,
    "averageReceivables": 19114500,
    "averagePayables": 117229000,
    "averageInventory": 72277500,
    "daysOfSalesOutstanding": 4.998381351120297,
    "daysOfPayablesOutstanding": 54.748949178448605,
    "daysOfInventoryOutstanding": 30.61826518914788,
    "operatingCycle": 35.61664654026818,
    "cashConversionCycle": -19.132302638180427,
    "freeCashFlowToEquity": -961180000,
    "freeCashFlowToFirm": -231921000,
    "tangibleAssetValue": 66487000,
    "netCurrentAssetValue": -846139000
  },
  {
    "symbol": "HIMS",
    "date": "2024-12-31",
    "fiscalYear": "2024",
    "period": "FY",
    "reportedCurrency": "USD",
    "marketCap": 5221405914.66,
    "enterpriseValue": 5012166914.66,
    "evToSales": 3.3945949138714564,
    "evToOperatingCashFlow": 19.962111941262684,
    "evToFreeCashFlow": 25.271344876118064,
    "evToEBITDA": 63.452379570583986,
    "netDebtToEBITDA": -2.6488967097517437,
    "currentRatio": 1.7881210839917423,
    "incomeQuality": 1.992129357812723,
    "grahamNumber": 5.38444214030887,
    "grahamNetNet": 0.49181241833545825,
    "taxBurden": 1.7575825187209773,
    "interestBurden": 1.15844143256385,
    "workingCapital": 174464000,
    "investedCapital": 423566000,
    "returnOnAssets": 0.17813576354094968,
    "operatingReturnOnAssets": 0.10777688306600797,
    "returnOnTangibleAssets": 0.22857775013102988,
    "returnOnEquity": 0.2643880213796055,
    "returnOnInvestedCapital": 0.126834555516626,
    "returnOnCapitalEmployed": 0.12732736562368874,
    "earningsYield": 0.024138709393599626,
    "freeCashFlowYield": 0.037984788626209465,
    "capexToOperatingCashFlow": 0.2100890538624524,
    "capexToDepreciation": 3.0869616104868913,
    "capexToRevenue": 0.03572604120245389,
    "salesGeneralAndAdministrativeToRevenue": 0.11362371098411529,
    "researchAndDevelopementToRevenue": 0.05338181690116044,
    "stockBasedCompensationToRevenue": 0.06252700617806536,
    "intangiblesToTotalAssets": 0.2206775880905505,
    "averageReceivables": 6414000,
    "averagePayables": 67125000,
    "averageInventory": 43445500,
    "daysOfSalesOutstanding": 1.5029996329191597,
    "daysOfPayablesOutstanding": 109.7000781201072,
    "daysOfInventoryOutstanding": 77.51312714459472,
    "operatingCycle": 79.01612677751388,
    "cashConversionCycle": -30.683951342593318,
    "freeCashFlowToEquity": 418668000,
    "freeCashFlowToFirm": 86353630.65638466,
    "tangibleAssetValue": 320578000,
    "netCurrentAssetValue": 165008000
  },
  {
    "symbol": "HIMS",
    "date": "2023-12-31",
    "fiscalYear": "2023",
    "period": "FY",
    "reportedCurrency": "USD",
    "marketCap": 1863167936.8000002,
    "enterpriseValue": 1776452936.8000002,
    "evToSales": 2.037216670642202,
    "evToOperatingCashFlow": 24.175019212607,
    "evToFreeCashFlow": 37.80411008065374,
    "evToEBITDA": -89.09885328518408,
    "netDebtToEBITDA": 4.349232621125489,
    "currentRatio": 2.996032463715694,
    "incomeQuality": -3.120827316741697,
    "grahamNumber": null,
    "grahamNetNet": 0.6693123445124327,
    "taxBurden": 1.091558110426035,
    "interestBurden": 0.7323871931551964,
    "workingCapital": 176585000,
    "investedCapital": 351771000,
    "returnOnAssets": -0.05336978054607354,
    "operatingReturnOnAssets": -0.07294616774423641,
    "returnOnTangibleAssets": -0.07553307178304372,
    "returnOnEquity": -0.06844190460687907,
    "returnOnInvestedCapital": -0.08320080000225989,
    "returnOnCapitalEmployed": -0.08350296837700373,
    "earningsYield": -0.012637615501499219,
    "freeCashFlowYield": 0.025221022255625152,
    "capexToOperatingCashFlow": 0.3605187594409591,
    "capexToDepreciation": 2.7842354177614292,
    "capexToRevenue": 0.03038073394495413,
    "salesGeneralAndAdministrativeToRevenue": 0.14894839449541283,
    "researchAndDevelopementToRevenue": 0.05530619266055046,
    "stockBasedCompensationToRevenue": 0.07577981651376146,
    "intangiblesToTotalAssets": 0.2934249953534337,
    "averageReceivables": 4989500,
    "averagePayables": 37716500,
    "averageInventory": 22013000,
    "daysOfSalesOutstanding": 2.824564220183486,
    "daysOfPayablesOutstanding": 100.09837568687878,
    "daysOfInventoryOutstanding": 52.20826355769782,
    "operatingCycle": 55.03282777788131,
    "cashConversionCycle": -45.06554790899747,
    "freeCashFlowToEquity": 142978000,
    "freeCashFlowToFirm": -47785661.026378006,
    "tangibleAssetValue": 214574000,
    "netCurrentAssetValue": 167896000
  },
  {
    "symbol": "HIMS",
    "date": "2022-12-31",
    "fiscalYear": "2022",
    "period": "FY",
    "reportedCurrency": "USD",
    "marketCap": 1310948329.2,
    "enterpriseValue": 1269483329.2,
    "evToSales": 2.4092707930675856,
    "evToOperatingCashFlow": -47.849056922091144,
    "evToFreeCashFlow": -37.583140778021196,
    "evToEBITDA": -20.7353989383075,
    "netDebtToEBITDA": 0.6772781471015795,
    "currentRatio": 4.517949145825076,
    "incomeQuality": 0.40395566247449677,
    "grahamNumber": null,
    "grahamNetNet": 0.6758843752756506,
    "taxBurden": 0.9995282229222785,
    "interestBurden": 0.9565046508581161,
    "workingCapital": 168654000,
    "investedCapital": 317511000,
    "returnOnAssets": -0.17928105235286249,
    "operatingReturnOnAssets": -0.17459583239084742,
    "returnOnTangibleAssets": -0.2811329557955475,
    "returnOnEquity": -0.2106813027481146,
    "returnOnInvestedCapital": -0.21453795977632728,
    "returnOnCapitalEmployed": -0.21575690954773868,
    "earningsYield": -0.050099609982400824,
    "freeCashFlowYield": -0.025766080361544732,
    "capexToOperatingCashFlow": -0.2731521616222532,
    "capexToDepreciation": 0.9696280438854696,
    "capexToRevenue": 0.013753615377024042,
    "salesGeneralAndAdministrativeToRevenue": 0.18635228385549119,
    "researchAndDevelopementToRevenue": 0.055487022599427616,
    "stockBasedCompensationToRevenue": 0.0812596315162189,
    "intangiblesToTotalAssets": 0.3622908710736718,
    "averageReceivables": 3404000,
    "averagePayables": 26001500,
    "averageInventory": 17560000,
    "daysOfSalesOutstanding": 2.2381461181668425,
    "daysOfPayablesOutstanding": 99.94157909876982,
    "daysOfInventoryOutstanding": 66.58654415621774,
    "operatingCycle": 68.82469027438458,
    "cashConversionCycle": -31.116888824385242,
    "freeCashFlowToEquity": 12220000,
    "freeCashFlowToFirm": -41874590.33009176,
    "tangibleAssetValue": 179019000,
    "netCurrentAssetValue": 161995000
  },
  {
    "symbol": "HIMS",
    "date": "2021-12-31",
    "fiscalYear": "2021",
    "period": "FY",
    "reportedCurrency": "USD",
    "marketCap": 1223419067.35,
    "enterpriseValue": 1157117067.35,
    "evToSales": 4.256015813526655,
    "evToOperatingCashFlow": -33.62539426217598,
    "evToFreeCashFlow": -29.354297860168952,
    "evToEBITDA": -10.42757817504303,
    "netDebtToEBITDA": 0.5974929483540151,
    "currentRatio": 3.406988046098888,
    "incomeQuality": 0.319638859733046,
    "grahamNumber": null,
    "grahamNetNet": 0.9142753226192801,
    "taxBurden": 0.9716954736224559,
    "interestBurden": 0.9630830479303211,
    "workingCapital": 190684000,
    "investedCapital": 332566000,
    "returnOnAssets": -0.2559744165864213,
    "operatingReturnOnAssets": -0.426648766322629,
    "returnOnTangibleAssets": -0.37932941997223535,
    "returnOnEquity": -0.32173606400114757,
    "returnOnInvestedCapital": -0.3261637931907559,
    "returnOnCapitalEmployed": -0.3370068314174898,
    "earningsYield": -0.08799846501754785,
    "freeCashFlowYield": -0.03222035772695937,
    "capexToOperatingCashFlow": -0.1455015692200395,
    "capexToDepreciation": 1.2287116564417178,
    "capexToRevenue": 0.01841634850925783,
    "salesGeneralAndAdministrativeToRevenue": 0.4180625133331862,
    "researchAndDevelopementToRevenue": 0.08231265494081905,
    "stockBasedCompensationToRevenue": 0.2472101457271276,
    "intangiblesToTotalAssets": 0.325192291688957,
    "averageReceivables": 2163500,
    "averagePayables": 13853000,
    "averageInventory": 8550500,
    "daysOfSalesOutstanding": 4.802172297868897,
    "daysOfPayablesOutstanding": 106.38430487949661,
    "daysOfInventoryOutstanding": 73.43983735011278,
    "operatingCycle": 78.24200964798167,
    "cashConversionCycle": -28.142295231514936,
    "freeCashFlowToEquity": 31058000,
    "freeCashFlowToFirm": -201370790.67647457,
    "tangibleAssetValue": 197848000,
    "netCurrentAssetValue": 183939000
  }
]
