[
  {
    "date": "2025-12-27",
    "symbol": "SAM",
    "reportedCurrency": "USD",
    "cik": "0000949870",
    "filingDate": "2026-02-24",
    "acceptedDate": "2026-02-24 17:09:03",
    "fiscalYear": "2025",
    "period": "FY",
    "netIncome": 108469000,
    "depreciationAndAmortization": 93992000,
    "deferredIncomeTax": -1018000,
    "stockBasedCompensation": 21754000,
    "changeInWorkingCapital": 47023000,
    "accountsReceivables": 4352000,
    "inventory": 23405000,
    "accountsPayables": 5227000,
    "otherWorkingCapital": 14039000,
    "otherNonCashItems": -62000,
    "netCashProvidedByOperatingActivities": 270158000,
    "investmentsInPropertyPlantAndEquipment": -54563000,
    "acquisitionsNet": 0,
    "purchasesOfInvestments": 0,
    "salesMaturitiesOfInvestments": 2513000,
    "otherInvestingActivities": -2466000,
    "netCashProvidedByInvestingActivities": -54516000,
    "netDebtIssuance": -1728000,
    "longTermNetDebtIssuance": -1728000,
    "shortTermNetDebtIssuance": 0,
    "netStockIssuance": -204868000,
    "netCommonStockIssuance": -204868000,
    "commonStockIssuance": 0,
    "commonStockRepurchased": -204868000,
    "netPreferredStockIssuance": 0,
    "netDividendsPaid": 0,
    "commonDividendsPaid": 0,
    "preferredDividendsPaid": 0,
    "otherFinancingActivities": 2513000,
    "netCashProvidedByFinancingActivities": -204083000,
    "effectOfForexChangesOnCash": 0,
    "netChangeInCash": 11559000,
    "cashAtEndOfPeriod": 223378000,
    "cashAtBeginningOfPeriod": 211819000,
    "operatingCashFlow": 270158000,
    "capitalExpenditure": -54563000,
    "freeCashFlow": 215595000,
    "incomeTaxesPaid": 0,
    "interestPaid": 0
  },
  {
    "date": "2024-12-28",
    "symbol": "SAM",
    "reportedCurrency": "USD",
    "cik": "0000949870",
    "filingDate": "2025-02-25",
    "acceptedDate": "2025-02-25 16:31:53",
    "fiscalYear": "2024",
    "period": "FY",
    "netIncome": 59695000,
    "depreciationAndAmortization": 93992000,
    "deferredIncomeTax": -19918000,
    "stockBasedCompensation": 18954000,
    "changeInWorkingCapital": 38916000,
    "accountsReceivables": 5548000,
    "inventory": 6907000,
    "accountsPayables": 2602000,
    "otherWorkingCapital": 23859000,
    "otherNonCashItems": 57253000,
    "netCashProvidedByOperatingActivities": 248892000,
    "investmentsInPropertyPlantAndEquipment": -76277000,
    "acquisitionsNet": 0,
    "purchasesOfInvestments": 0,
    "salesMaturitiesOfInvestments": 0,
    "otherInvestingActivities": -19977000,
    "netCashProvidedByInvestingActivities": -96254000,
    "netDebtIssuance": -1886000,
    "longTermNetDebtIssuance": -1886000,
    "shortTermNetDebtIssuance": 0,
    "netStockIssuance": -238614000,
    "netCommonStockIssuance": -238614000,
    "commonStockIssuance": 0,
    "commonStockRepurchased": -238614000,
    "netPreferredStockIssuance": 0,
    "netDividendsPaid": 0,
    "commonDividendsPaid": 0,
    "preferredDividendsPaid": 0,
    "otherFinancingActivities": 1190000,
    "netCashProvidedByFinancingActivities": -239310000,
    "effectOfForexChangesOnCash": 0,
    "netChangeInCash": -86672000,
    "cashAtEndOfPeriod": 211819000,
    "cashAtBeginningOfPeriod": 298491000,
    "operatingCashFlow": 248892000,
    "capitalExpenditure": -76277000,
    "freeCashFlow": 172615000,
    "incomeTaxesPaid": 0,
    "interestPaid": 0
  },
  {
    "date": "2023-12-31",
    "symbol": "SAM",
    "reportedCurrency": "USD",
    "cik": "0000949870",
    "filingDate": "2024-02-27",
    "acceptedDate": "2024-02-27 16:20:38",
    "fiscalYear": "2023",
    "period": "FY",
    "netIncome": 76250000,
    "depreciationAndAmortization": 88141000,
    "deferredIncomeTax": -10871000,
    "stockBasedCompensation": 16971000,
    "changeInWorkingCapital": 64936000,
    "accountsReceivables": -10340000,
    "inventory": 31500000,
    "accountsPayables": 2763000,
    "otherWorkingCapital": 41013000,
    "otherNonCashItems": 29724000,
    "netCashProvidedByOperatingActivities": 265151000,
    "investmentsInPropertyPlantAndEquipment": -64087000,
    "acquisitionsNet": 0,
    "purchasesOfInvestments": 0,
    "salesMaturitiesOfInvestments": 0,
    "otherInvestingActivities": 1709000,
    "netCashProvidedByInvestingActivities": -62378000,
    "netDebtIssuance": -1575000,
    "longTermNetDebtIssuance": -1575000,
    "shortTermNetDebtIssuance": 0,
    "netStockIssuance": -92877000,
    "netCommonStockIssuance": -92877000,
    "commonStockIssuance": 0,
    "commonStockRepurchased": -92877000,
    "netPreferredStockIssuance": 0,
    "netDividendsPaid": 0,
    "commonDividendsPaid": 0,
    "preferredDividendsPaid": 0,
    "otherFinancingActivities": 9610000,
    "netCashProvidedByFinancingActivities": -84842000,
    "effectOfForexChangesOnCash": 0,
    "netChangeInCash": 117931000,
    "cashAtEndOfPeriod": 298491000,
    "cashAtBeginningOfPeriod": 180560000,
    "operatingCashFlow": 265151000,
    "capitalExpenditure": -64087000,
    "freeCashFlow": 201064000,
    "incomeTaxesPaid": 0,
    "interestPaid": 0
  },
  {
    "date": "2022-12-31",
    "symbol": "SAM",
    "reportedCurrency": "USD",
    "cik": "0000949870",
    "filingDate": "2023-02-22",
    "acceptedDate": "2023-02-22 16:52:15",
    "fiscalYear": "2022",
    "period": "FY",
    "netIncome": 67263000,
    "depreciationAndAmortization": 81356000,
    "deferredIncomeTax": 9097000,
    "stockBasedCompensation": 13988000,
    "changeInWorkingCapital": -9702000,
    "accountsReceivables": -2042000,
    "inventory": 131000,
    "accountsPayables": -2219000,
    "otherWorkingCapital": -5572000,
    "otherNonCashItems": 37943000,
    "netCashProvidedByOperatingActivities": 199945000,
    "investmentsInPropertyPlantAndEquipment": -90582000,
    "acquisitionsNet": 0,
    "purchasesOfInvestments": 0,
    "salesMaturitiesOfInvestments": 0,
    "otherInvestingActivities": 2076000,
    "netCashProvidedByInvestingActivities": -88506000,
    "netDebtIssuance": -1672000,
    "longTermNetDebtIssuance": -1672000,
    "shortTermNetDebtIssuance": 0,
    "netStockIssuance": 0,
    "netCommonStockIssuance": 0,
    "commonStockIssuance": 0,
    "commonStockRepurchased": 0,
    "netPreferredStockIssuance": 0,
    "netDividendsPaid": 0,
    "commonDividendsPaid": 0,
    "preferredDividendsPaid": 0,
    "otherFinancingActivities": 4472000,
    "netCashProvidedByFinancingActivities": 2800000,
    "effectOfForexChangesOnCash": 0,
    "netChangeInCash": 114239000,
    "cashAtEndOfPeriod": 180560000,
    "cashAtBeginningOfPeriod": 66321000,
    "operatingCashFlow": 199945000,
    "capitalExpenditure": -90582000,
    "freeCashFlow": 109363000,
    "incomeTaxesPaid": 28144000,
    "interestPaid": 0
  },
  {
    "date": "2021-12-31",
    "symbol": "SAM",
    "reportedCurrency": "USD",
    "cik": "0000949870",
    "filingDate": "2022-02-22",
    "acceptedDate": "2022-02-22 16:20:20",
    "fiscalYear": "2021",
    "period": "FY",
    "netIncome": 14553000,
    "depreciationAndAmortization": 80114000,
    "deferredIncomeTax": -5225000,
    "stockBasedCompensation": 0,
    "changeInWorkingCapital": -69860000,
    "accountsReceivables": 23071000,
    "inventory": -21224000,
    "accountsPayables": -27361000,
    "otherWorkingCapital": -44346000,
    "otherNonCashItems": 36715000,
    "netCashProvidedByOperatingActivities": 56297000,
    "investmentsInPropertyPlantAndEquipment": -147919000,
    "acquisitionsNet": 1157000,
    "purchasesOfInvestments": 0,
    "salesMaturitiesOfInvestments": 0,
    "otherInvestingActivities": 145000,
    "netCashProvidedByInvestingActivities": -146617000,
    "netDebtIssuance": -1570000,
    "longTermNetDebtIssuance": -1570000,
    "shortTermNetDebtIssuance": 0,
    "netStockIssuance": 10465000,
    "netCommonStockIssuance": 10465000,
    "commonStockIssuance": 10465000,
    "commonStockRepurchased": 0,
    "netPreferredStockIssuance": 0,
    "netDividendsPaid": 0,
    "commonDividendsPaid": 0,
    "preferredDividendsPaid": 0,
    "otherFinancingActivities": -15536000,
    "netCashProvidedByFinancingActivities": -6641000,
    "effectOfForexChangesOnCash": 0,
    "netChangeInCash": -96961000,
    "cashAtEndOfPeriod": 66321000,
    "cashAtBeginningOfPeriod": 163282000,
    "operatingCashFlow": 56297000,
    "capitalExpenditure": -147919000,
    "freeCashFlow": -91622000,
    "incomeTaxesPaid": 0,
    "interestPaid": 0
  },
  {
    "date": "2020-12-31",
    "symbol": "SAM",
    "reportedCurrency": "USD",
    "cik": "0000949870",
    "filingDate": "2021-02-17",
    "acceptedDate": "2021-02-17 16:37:19",
    "fiscalYear": "2020",
    "period": "FY",
    "netIncome": 191960000,
    "depreciationAndAmortization": 73012000,
    "deferredIncomeTax": 17655000,
    "stockBasedCompensation": 0,
    "changeInWorkingCapital": -48817000,
    "accountsReceivables": -24014000,
    "inventory": -24463000,
    "accountsPayables": 40771000,
    "otherWorkingCapital": -41111000,
    "otherNonCashItems": 19597000,
    "netCashProvidedByOperatingActivities": 253407000,
    "investmentsInPropertyPlantAndEquipment": -139996000,
    "acquisitionsNet": 487000,
    "purchasesOfInvestments": 0,
    "salesMaturitiesOfInvestments": 0,
    "otherInvestingActivities": 392000,
    "netCashProvidedByInvestingActivities": -139117000,
    "netDebtIssuance": -1260000,
    "longTermNetDebtIssuance": -1260000,
    "shortTermNetDebtIssuance": 0,
    "netStockIssuance": 15274000,
    "netCommonStockIssuance": 15274000,
    "commonStockIssuance": 15274000,
    "commonStockRepurchased": 0,
    "netPreferredStockIssuance": 0,
    "netDividendsPaid": 0,
    "commonDividendsPaid": 0,
    "preferredDividendsPaid": 0,
    "otherFinancingActivities": -1691999,
    "netCashProvidedByFinancingActivities": 12322000,
    "effectOfForexChangesOnCash": 0,
    "netChangeInCash": 126612000,
    "cashAtEndOfPeriod": 163282000,
    "cashAtBeginningOfPeriod": 36670000,
    "operatingCashFlow": 253407000,
    "capitalExpenditure": -139996000,
    "freeCashFlow": 113411000,
    "incomeTaxesPaid": 0,
    "interestPaid": 0
  },
  {
    "date": "2019-12-31",
    "symbol": "SAM",
    "reportedCurrency": "USD",
    "cik": "0000949870",
    "filingDate": "2020-02-19",
    "acceptedDate": "2020-02-19 16:28:03",
    "fiscalYear": "2019",
    "period": "FY",
    "netIncome": 110041000,
    "depreciationAndAmortization": 56271000,
    "deferredIncomeTax": 7404000,
    "stockBasedCompensation": 12337000,
    "changeInWorkingCapital": -13845000,
    "accountsReceivables": -12260000,
    "inventory": -24932000,
    "accountsPayables": 21417000,
    "otherWorkingCapital": 1930000,
    "otherNonCashItems": 6034000,
    "netCashProvidedByOperatingActivities": 178242000,
    "investmentsInPropertyPlantAndEquipment": -93233000,
    "acquisitionsNet": -165517000,
    "purchasesOfInvestments": 0,
    "salesMaturitiesOfInvestments": 0,
    "otherInvestingActivities": -79000,
    "netCashProvidedByInvestingActivities": -258829000,
    "netDebtIssuance": -378000,
    "longTermNetDebtIssuance": -378000,
    "shortTermNetDebtIssuance": 0,
    "netStockIssuance": 1173000,
    "netCommonStockIssuance": 1173000,
    "commonStockIssuance": 1173000,
    "commonStockRepurchased": 0,
    "netPreferredStockIssuance": 0,
    "netDividendsPaid": 0,
    "commonDividendsPaid": 0,
    "preferredDividendsPaid": 0,
    "otherFinancingActivities": 8063000,
    "netCashProvidedByFinancingActivities": 8858000,
    "effectOfForexChangesOnCash": 0,
    "netChangeInCash": -71729000,
    "cashAtEndOfPeriod": 36670000,
    "cashAtBeginningOfPeriod": 108399000,
    "operatingCashFlow": 178242000,
    "capitalExpenditure": -93233000,
    "freeCashFlow": 85009000,
    "incomeTaxesPaid": 30760000,
    "interestPaid": 0
  },
  {
    "date": "2018-12-31",
    "symbol": "SAM",
    "reportedCurrency": "USD",
    "cik": "0000949870",
    "filingDate": "2019-02-20",
    "acceptedDate": "2019-02-20 16:33:00",
    "fiscalYear": "2018",
    "period": "FY",
    "netIncome": 92663000,
    "depreciationAndAmortization": 51968000,
    "deferredIncomeTax": 14350000,
    "stockBasedCompensation": 10035000,
    "changeInWorkingCapital": -6287000,
    "accountsReceivables": -1636000,
    "inventory": -21312000,
    "accountsPayables": 6352000,
    "otherWorkingCapital": 10309000,
    "otherNonCashItems": 718000,
    "netCashProvidedByOperatingActivities": 163447000,
    "investmentsInPropertyPlantAndEquipment": -55510000,
    "acquisitionsNet": 27000,
    "purchasesOfInvestments": 0,
    "salesMaturitiesOfInvestments": 906000,
    "otherInvestingActivities": -740000,
    "netCashProvidedByInvestingActivities": -55344000,
    "netDebtIssuance": -78000,
    "longTermNetDebtIssuance": -78000,
    "shortTermNetDebtIssuance": 0,
    "netStockIssuance": -88312000,
    "netCommonStockIssuance": -88312000,
    "commonStockIssuance": 0,
    "commonStockRepurchased": -88312000,
    "netPreferredStockIssuance": 0,
    "netDividendsPaid": 0,
    "commonDividendsPaid": 0,
    "preferredDividendsPaid": 0,
    "otherFinancingActivities": 23049000,
    "netCashProvidedByFinancingActivities": -65341000,
    "effectOfForexChangesOnCash": 0,
    "netChangeInCash": 42762000,
    "cashAtEndOfPeriod": 108399000,
    "cashAtBeginningOfPeriod": 65637000,
    "operatingCashFlow": 163447000,
    "capitalExpenditure": -55510000,
    "freeCashFlow": 107937000,
    "incomeTaxesPaid": 11353000,
    "interestPaid": 0
  },
  {
    "date": "2017-12-31",
    "symbol": "SAM",
    "reportedCurrency": "USD",
    "cik": "0000949870",
    "filingDate": "2018-02-21",
    "acceptedDate": "2018-02-21 16:31:16",
    "fiscalYear": "2017",
    "period": "FY",
    "netIncome": 99049000,
    "depreciationAndAmortization": 51256000,
    "deferredIncomeTax": -22442000,
    "stockBasedCompensation": 6316000,
    "changeInWorkingCapital": -1412000,
    "accountsReceivables": 2945000,
    "inventory": -1741000,
    "accountsPayables": 245000,
    "otherWorkingCapital": -2861000,
    "otherNonCashItems": 3215000,
    "netCashProvidedByOperatingActivities": 135982000,
    "investmentsInPropertyPlantAndEquipment": -32987000,
    "acquisitionsNet": 25000,
    "purchasesOfInvestments": 0,
    "salesMaturitiesOfInvestments": 33000,
    "otherInvestingActivities": 58000,
    "netCashProvidedByInvestingActivities": -32929000,
    "netDebtIssuance": -60000,
    "longTermNetDebtIssuance": -60000,
    "shortTermNetDebtIssuance": 0,
    "netStockIssuance": -144602000,
    "netCommonStockIssuance": -143806000,
    "commonStockIssuance": 796000,
    "commonStockRepurchased": -144602000,
    "netPreferredStockIssuance": -796000,
    "netDividendsPaid": 0,
    "commonDividendsPaid": 0,
    "preferredDividendsPaid": 0,
    "otherFinancingActivities": 16211000,
    "netCashProvidedByFinancingActivities": -128451000,
    "effectOfForexChangesOnCash": 0,
    "netChangeInCash": -25398000,
    "cashAtEndOfPeriod": 65637000,
    "cashAtBeginningOfPeriod": 91035000,
    "operatingCashFlow": 135982000,
    "capitalExpenditure": -32987000,
    "freeCashFlow": 102995000,
    "incomeTaxesPaid": 43006000,
    "interestPaid": 0
  },
  {
    "date": "2016-12-31",
    "symbol": "SAM",
    "reportedCurrency": "USD",
    "cik": "0000949870",
    "filingDate": "2017-02-22",
    "acceptedDate": "2017-02-22 16:36:07",
    "fiscalYear": "2016",
    "period": "FY",
    "netIncome": 87349000,
    "depreciationAndAmortization": 49557000,
    "deferredIncomeTax": 8243000,
    "stockBasedCompensation": 6148000,
    "changeInWorkingCapital": 15279000,
    "accountsReceivables": 2534000,
    "inventory": 445000,
    "accountsPayables": -1811000,
    "otherWorkingCapital": 14111000,
    "otherNonCashItems": -12387000,
    "netCashProvidedByOperatingActivities": 154189000,
    "investmentsInPropertyPlantAndEquipment": -49913000,
    "acquisitionsNet": 3855000,
    "purchasesOfInvestments": 0,
    "salesMaturitiesOfInvestments": 736000,
    "otherInvestingActivities": 3159000,
    "netCashProvidedByInvestingActivities": -46018000,
    "netDebtIssuance": -58000,
    "longTermNetDebtIssuance": -58000,
    "shortTermNetDebtIssuance": 0,
    "netStockIssuance": -164658000,
    "netCommonStockIssuance": -163922000,
    "commonStockIssuance": 736000,
    "commonStockRepurchased": -164658000,
    "netPreferredStockIssuance": -736000,
    "netDividendsPaid": 0,
    "commonDividendsPaid": 0,
    "preferredDividendsPaid": 0,
    "otherFinancingActivities": 53387000,
    "netCashProvidedByFinancingActivities": -111329000,
    "effectOfForexChangesOnCash": 0,
    "netChangeInCash": -3158000,
    "cashAtEndOfPeriod": 91035000,
    "cashAtBeginningOfPeriod": 94193000,
    "operatingCashFlow": 154189000,
    "capitalExpenditure": -49913000,
    "freeCashFlow": 104276000,
    "incomeTaxesPaid": 30978000,
    "interestPaid": 0
  }
]
