[
  {
    "date": "2025-12-31",
    "symbol": "CPS",
    "reportedCurrency": "USD",
    "cik": "0001320461",
    "filingDate": "2026-02-13",
    "acceptedDate": "2026-02-13 16:20:46",
    "fiscalYear": "2025",
    "period": "FY",
    "cashAndCashEquivalents": 198280000,
    "shortTermInvestments": 0,
    "cashAndShortTermInvestments": 198280000,
    "netReceivables": 465411000,
    "accountsReceivables": 334267000,
    "otherReceivables": 131144000,
    "inventory": 154189000,
    "prepaids": 23940000,
    "otherCurrentAssets": 39280000,
    "totalCurrentAssets": 881100000,
    "propertyPlantEquipmentNet": 606982000,
    "goodwill": 140696000,
    "intangibleAssets": 28978000,
    "goodwillAndIntangibleAssets": 169674000,
    "longTermInvestments": 1602000,
    "taxAssets": 103112000,
    "otherNonCurrentAssets": 70704000,
    "totalNonCurrentAssets": 952074000,
    "otherAssets": 0,
    "totalAssets": 1833174000,
    "totalPayables": 337319000,
    "accountPayables": 337319000,
    "otherPayables": 0,
    "accruedExpenses": 122395000,
    "shortTermDebt": 104533000,
    "capitalLeaseObligationsCurrent": 0,
    "taxPayables": 0,
    "deferredRevenue": 0,
    "otherCurrentLiabilities": 114150000,
    "totalCurrentLiabilities": 678397000,
    "longTermDebt": 1088289000,
    "capitalLeaseObligationsNonCurrent": 69806000,
    "deferredRevenueNonCurrent": 0,
    "deferredTaxLiabilitiesNonCurrent": 3475000,
    "otherNonCurrentLiabilities": 84783999,
    "totalNonCurrentLiabilities": 1246353999,
    "otherLiabilities": 0,
    "capitalLeaseObligations": 69806000,
    "totalLiabilities": 1924751000,
    "treasuryStock": 0,
    "preferredStock": 0,
    "commonStock": 17000,
    "retainedEarnings": -474727000,
    "additionalPaidInCapital": 524312000,
    "accumulatedOtherComprehensiveIncomeLoss": -133090000,
    "otherTotalStockholdersEquity": 0,
    "totalStockholdersEquity": -83488000,
    "totalEquity": -91577000,
    "minorityInterest": -8089000,
    "totalLiabilitiesAndTotalEquity": 1833174000,
    "totalInvestments": 1602000,
    "totalDebt": 1262628000,
    "netDebt": 1064348000
  },
  {
    "date": "2024-12-31",
    "symbol": "CPS",
    "reportedCurrency": "USD",
    "cik": "0001320461",
    "filingDate": "2025-02-14",
    "acceptedDate": "2025-02-14 16:10:05",
    "fiscalYear": "2024",
    "period": "FY",
    "cashAndCashEquivalents": 170035000,
    "shortTermInvestments": 0,
    "cashAndShortTermInvestments": 170035000,
    "netReceivables": 436638000,
    "accountsReceivables": 310738000,
    "otherReceivables": 125900000,
    "inventory": 142401000,
    "prepaids": 25833000,
    "otherCurrentAssets": 30349000,
    "totalCurrentAssets": 805256000,
    "propertyPlantEquipmentNet": 626493000,
    "goodwill": 140443000,
    "intangibleAssets": 33805000,
    "goodwillAndIntangibleAssets": 174248000,
    "longTermInvestments": 1072000,
    "taxAssets": 63240000,
    "otherNonCurrentAssets": 62756000,
    "totalNonCurrentAssets": 927809000,
    "otherAssets": 0,
    "totalAssets": 1733065000,
    "totalPayables": 295178000,
    "accountPayables": 295178000,
    "otherPayables": 0,
    "accruedExpenses": 220318000,
    "shortTermDebt": 42428000,
    "capitalLeaseObligationsCurrent": 18859000,
    "taxPayables": 0,
    "deferredRevenue": 0,
    "otherCurrentLiabilities": 0,
    "totalCurrentLiabilities": 576783000,
    "longTermDebt": 1041538000,
    "capitalLeaseObligationsNonCurrent": 88208000,
    "deferredRevenueNonCurrent": 0,
    "deferredTaxLiabilitiesNonCurrent": 3801000,
    "otherNonCurrentLiabilities": 156105000,
    "totalNonCurrentLiabilities": 1289652000,
    "otherLiabilities": 0,
    "capitalLeaseObligations": 107067000,
    "totalLiabilities": 1866435000,
    "treasuryStock": 0,
    "preferredStock": 0,
    "commonStock": 17000,
    "retainedEarnings": -470562000,
    "additionalPaidInCapital": 518208000,
    "accumulatedOtherComprehensiveIncomeLoss": -173432000,
    "otherTotalStockholdersEquity": 0,
    "totalStockholdersEquity": -125769000,
    "totalEquity": -133370000,
    "minorityInterest": -7601000,
    "totalLiabilitiesAndTotalEquity": 1733065000,
    "totalInvestments": 1072000,
    "totalDebt": 1191033000,
    "netDebt": 1020998000
  },
  {
    "date": "2023-12-31",
    "symbol": "CPS",
    "reportedCurrency": "USD",
    "cik": "0001320461",
    "filingDate": "2024-02-16",
    "acceptedDate": "2024-02-16 16:11:31",
    "fiscalYear": "2023",
    "period": "FY",
    "cashAndCashEquivalents": 154801000,
    "shortTermInvestments": 0,
    "cashAndShortTermInvestments": 154801000,
    "netReceivables": 541696000,
    "accountsReceivables": 380562000,
    "otherReceivables": 161134000,
    "inventory": 146846000,
    "prepaids": 28328000,
    "otherCurrentAssets": 28915000,
    "totalCurrentAssets": 900586000,
    "propertyPlantEquipmentNet": 699557000,
    "goodwill": 140814000,
    "intangibleAssets": 40568000,
    "goodwillAndIntangibleAssets": 181382000,
    "longTermInvestments": 1016000,
    "taxAssets": 23792000,
    "otherNonCurrentAssets": 65966000,
    "totalNonCurrentAssets": 971713000,
    "otherAssets": 0,
    "totalAssets": 1872299000,
    "totalPayables": 334578000,
    "accountPayables": 334578000,
    "otherPayables": 0,
    "accruedExpenses": 249376000,
    "shortTermDebt": 50712000,
    "capitalLeaseObligationsCurrent": 18577000,
    "taxPayables": 0,
    "deferredRevenue": 0,
    "otherCurrentLiabilities": 0,
    "totalCurrentLiabilities": 653243000,
    "longTermDebt": 1024985000,
    "capitalLeaseObligationsNonCurrent": 96233000,
    "deferredRevenueNonCurrent": 0,
    "deferredTaxLiabilitiesNonCurrent": 5208000,
    "otherNonCurrentLiabilities": 182363000,
    "totalNonCurrentLiabilities": 1308789000,
    "otherLiabilities": 0,
    "capitalLeaseObligations": 114810000,
    "totalLiabilities": 1962032000,
    "treasuryStock": 0,
    "preferredStock": 0,
    "commonStock": 17000,
    "retainedEarnings": -391816000,
    "additionalPaidInCapital": 512164000,
    "accumulatedOtherComprehensiveIncomeLoss": -201665000,
    "otherTotalStockholdersEquity": 0,
    "totalStockholdersEquity": -81300000,
    "totalEquity": -89733000,
    "minorityInterest": -8433000,
    "totalLiabilitiesAndTotalEquity": 1872299000,
    "totalInvestments": 1016000,
    "totalDebt": 1190507000,
    "netDebt": 1035706000
  },
  {
    "date": "2022-12-31",
    "symbol": "CPS",
    "reportedCurrency": "USD",
    "cik": "0001320461",
    "filingDate": "2023-02-17",
    "acceptedDate": "2023-02-17 16:03:39",
    "fiscalYear": "2022",
    "period": "FY",
    "cashAndCashEquivalents": 186875000,
    "shortTermInvestments": 0,
    "cashAndShortTermInvestments": 186875000,
    "netReceivables": 512735000,
    "accountsReceivables": 358700000,
    "otherReceivables": 154035000,
    "inventory": 157756000,
    "prepaids": 31170000,
    "otherCurrentAssets": 57113000,
    "totalCurrentAssets": 945649000,
    "propertyPlantEquipmentNet": 737431000,
    "goodwill": 142023000,
    "intangibleAssets": 47641000,
    "goodwillAndIntangibleAssets": 189664000,
    "longTermInvestments": 1282000,
    "taxAssets": 19852000,
    "otherNonCurrentAssets": 69651000,
    "totalNonCurrentAssets": 1017880000,
    "otherAssets": 0,
    "totalAssets": 1963529000,
    "totalPayables": 338210000,
    "accountPayables": 338210000,
    "otherPayables": 0,
    "accruedExpenses": 218492000,
    "shortTermDebt": 54130000,
    "capitalLeaseObligationsCurrent": 23014000,
    "taxPayables": 0,
    "deferredRevenue": 0,
    "otherCurrentLiabilities": -2228000,
    "totalCurrentLiabilities": 631618000,
    "longTermDebt": 982054000,
    "capitalLeaseObligationsNonCurrent": 77617000,
    "deferredRevenueNonCurrent": 0,
    "deferredTaxLiabilitiesNonCurrent": 7052000,
    "otherNonCurrentLiabilities": 163996000,
    "totalNonCurrentLiabilities": 1230719000,
    "otherLiabilities": 0,
    "capitalLeaseObligations": 100631000,
    "totalLiabilities": 1862337000,
    "treasuryStock": 0,
    "preferredStock": 0,
    "commonStock": 17000,
    "retainedEarnings": -189831000,
    "additionalPaidInCapital": 507498000,
    "accumulatedOtherComprehensiveIncomeLoss": -209971000,
    "otherTotalStockholdersEquity": 0,
    "totalStockholdersEquity": 107713000,
    "totalEquity": 101192000,
    "minorityInterest": -6521000,
    "totalLiabilitiesAndTotalEquity": 1963529000,
    "totalInvestments": 1282000,
    "totalDebt": 1134587000,
    "netDebt": 947712000
  },
  {
    "date": "2021-12-31",
    "symbol": "CPS",
    "reportedCurrency": "USD",
    "cik": "0001320461",
    "filingDate": "2022-02-18",
    "acceptedDate": "2022-02-18 16:04:15",
    "fiscalYear": "2021",
    "period": "FY",
    "cashAndCashEquivalents": 248971000,
    "shortTermInvestments": 0,
    "cashAndShortTermInvestments": 248971000,
    "netReceivables": 489182000,
    "accountsReceivables": 317469000,
    "otherReceivables": 171713000,
    "inventory": 158075000,
    "prepaids": 26313000,
    "otherCurrentAssets": 72356000,
    "totalCurrentAssets": 994897000,
    "propertyPlantEquipmentNet": 913697000,
    "goodwill": 142282000,
    "intangibleAssets": 60375000,
    "goodwillAndIntangibleAssets": 202657000,
    "longTermInvestments": 2157000,
    "taxAssets": 27805000,
    "otherNonCurrentAssets": 85280000,
    "totalNonCurrentAssets": 1231596000,
    "otherAssets": 0,
    "totalAssets": 2226493000,
    "totalPayables": 348133000,
    "accountPayables": 348133000,
    "otherPayables": 0,
    "accruedExpenses": 69353000,
    "shortTermDebt": 78663000,
    "capitalLeaseObligationsCurrent": 0,
    "taxPayables": 0,
    "deferredRevenue": 0,
    "otherCurrentLiabilities": 101466000,
    "totalCurrentLiabilities": 597615000,
    "longTermDebt": 957014000,
    "capitalLeaseObligationsNonCurrent": 116350000,
    "deferredRevenueNonCurrent": 0,
    "deferredTaxLiabilitiesNonCurrent": 8414000,
    "otherNonCurrentLiabilities": 215740000,
    "totalNonCurrentLiabilities": 1297518000,
    "otherLiabilities": 0,
    "capitalLeaseObligations": 116350000,
    "totalLiabilities": 1895133000,
    "treasuryStock": 0,
    "preferredStock": 0,
    "commonStock": 17000,
    "retainedEarnings": 25553000,
    "additionalPaidInCapital": 504497000,
    "accumulatedOtherComprehensiveIncomeLoss": -205184000,
    "otherTotalStockholdersEquity": 0,
    "totalStockholdersEquity": 324883000,
    "totalEquity": 331360000,
    "minorityInterest": 6477000,
    "totalLiabilitiesAndTotalEquity": 2226493000,
    "totalInvestments": 2157000,
    "totalDebt": 1152027000,
    "netDebt": 903056000
  },
  {
    "date": "2020-12-31",
    "symbol": "CPS",
    "reportedCurrency": "USD",
    "cik": "0001320461",
    "filingDate": "2021-02-22",
    "acceptedDate": "2021-02-22 17:24:45",
    "fiscalYear": "2020",
    "period": "FY",
    "cashAndCashEquivalents": 438438000,
    "shortTermInvestments": 0,
    "cashAndShortTermInvestments": 438438000,
    "netReceivables": 547691000,
    "accountsReceivables": 379564000,
    "otherReceivables": 168127000,
    "inventory": 143742000,
    "prepaids": 29748000,
    "otherCurrentAssets": 100110000,
    "totalCurrentAssets": 1259729000,
    "propertyPlantEquipmentNet": 1002104000,
    "goodwill": 142250000,
    "intangibleAssets": 67679000,
    "goodwillAndIntangibleAssets": 209929000,
    "longTermInvestments": 1051000,
    "taxAssets": 66111000,
    "otherNonCurrentAssets": 73020000,
    "totalNonCurrentAssets": 1352215000,
    "otherAssets": 0,
    "totalAssets": 2611944000,
    "totalPayables": 385284000,
    "accountPayables": 385284000,
    "otherPayables": 0,
    "accruedExpenses": 223554000,
    "shortTermDebt": 40731000,
    "capitalLeaseObligationsCurrent": 24011000,
    "taxPayables": 0,
    "deferredRevenue": 0,
    "otherCurrentLiabilities": -2300000,
    "totalCurrentLiabilities": 671280000,
    "longTermDebt": 956608000,
    "capitalLeaseObligationsNonCurrent": 116669000,
    "deferredRevenueNonCurrent": 0,
    "deferredTaxLiabilitiesNonCurrent": 8638000,
    "otherNonCurrentLiabilities": 234638000,
    "totalNonCurrentLiabilities": 1316553000,
    "otherLiabilities": 0,
    "capitalLeaseObligations": 140680000,
    "totalLiabilities": 1987833000,
    "treasuryStock": 0,
    "preferredStock": 0,
    "commonStock": 17000,
    "retainedEarnings": 350270000,
    "additionalPaidInCapital": 498719000,
    "accumulatedOtherComprehensiveIncomeLoss": -241896000,
    "otherTotalStockholdersEquity": 0,
    "totalStockholdersEquity": 607110000,
    "totalEquity": 624111000,
    "minorityInterest": 17001000,
    "totalLiabilitiesAndTotalEquity": 2611944000,
    "totalInvestments": 1051000,
    "totalDebt": 1135719000,
    "netDebt": 697281000
  },
  {
    "date": "2019-12-31",
    "symbol": "CPS",
    "reportedCurrency": "USD",
    "cik": "0001320461",
    "filingDate": "2020-02-26",
    "acceptedDate": "2020-02-26 17:16:29",
    "fiscalYear": "2019",
    "period": "FY",
    "cashAndCashEquivalents": 359548000,
    "shortTermInvestments": 0,
    "cashAndShortTermInvestments": 359548000,
    "netReceivables": 571330000,
    "accountsReceivables": 423155000,
    "otherReceivables": 148175000,
    "inventory": 143439000,
    "prepaids": 34452000,
    "otherCurrentAssets": 93501000,
    "totalCurrentAssets": 1202270000,
    "propertyPlantEquipmentNet": 1090838000,
    "goodwill": 142187000,
    "intangibleAssets": 84369000,
    "goodwillAndIntangibleAssets": 226556000,
    "longTermInvestments": 2194000,
    "taxAssets": 56662000,
    "otherNonCurrentAssets": 57062000,
    "totalNonCurrentAssets": 1433312000,
    "otherAssets": 0,
    "totalAssets": 2635582000,
    "totalPayables": 426055000,
    "accountPayables": 426055000,
    "otherPayables": 0,
    "accruedExpenses": 88486000,
    "shortTermDebt": 85543000,
    "capitalLeaseObligationsCurrent": 0,
    "taxPayables": 0,
    "deferredRevenue": 0,
    "otherCurrentLiabilities": 119841000,
    "totalCurrentLiabilities": 719925000,
    "longTermDebt": 708479000,
    "capitalLeaseObligationsNonCurrent": 97934000,
    "deferredRevenueNonCurrent": 0,
    "deferredTaxLiabilitiesNonCurrent": 10785000,
    "otherNonCurrentLiabilities": 222477000,
    "totalNonCurrentLiabilities": 1039675000,
    "otherLiabilities": 0,
    "capitalLeaseObligations": 97934000,
    "totalLiabilities": 1759600000,
    "treasuryStock": 0,
    "preferredStock": 0,
    "commonStock": 17000,
    "retainedEarnings": 619448000,
    "additionalPaidInCapital": 490451000,
    "accumulatedOtherComprehensiveIncomeLoss": -253741000,
    "otherTotalStockholdersEquity": 0,
    "totalStockholdersEquity": 856175000,
    "totalEquity": 875982000,
    "minorityInterest": 19807000,
    "totalLiabilitiesAndTotalEquity": 2635582000,
    "totalInvestments": 2194000,
    "totalDebt": 891956000,
    "netDebt": 532408000
  },
  {
    "date": "2018-12-31",
    "symbol": "CPS",
    "reportedCurrency": "USD",
    "cik": "0001320461",
    "filingDate": "2019-02-25",
    "acceptedDate": "2019-02-25 17:02:25",
    "fiscalYear": "2018",
    "period": "FY",
    "cashAndCashEquivalents": 264980000,
    "shortTermInvestments": 0,
    "cashAndShortTermInvestments": 264980000,
    "netReceivables": 559713000,
    "accountsReceivables": 418607000,
    "otherReceivables": 141106000,
    "inventory": 175572000,
    "prepaids": 36878000,
    "otherCurrentAssets": 212581000,
    "totalCurrentAssets": 1249724000,
    "propertyPlantEquipmentNet": 984241000,
    "goodwill": 143681000,
    "intangibleAssets": 99602000,
    "goodwillAndIntangibleAssets": 243283000,
    "longTermInvestments": 2401000,
    "taxAssets": 70007000,
    "otherNonCurrentAssets": 73447000,
    "totalNonCurrentAssets": 1373379000,
    "otherAssets": 0,
    "totalAssets": 2623103000,
    "totalPayables": 452320000,
    "accountPayables": 452320000,
    "otherPayables": 0,
    "accruedExpenses": 92604000,
    "shortTermDebt": 101323000,
    "capitalLeaseObligationsCurrent": 0,
    "taxPayables": 0,
    "deferredRevenue": 191511000,
    "otherCurrentLiabilities": 174171000,
    "totalCurrentLiabilities": 816349000,
    "longTermDebt": 729805000,
    "capitalLeaseObligationsNonCurrent": 10297000,
    "deferredRevenueNonCurrent": -184395000,
    "deferredTaxLiabilitiesNonCurrent": 8233000,
    "otherNonCurrentLiabilities": 212150000,
    "totalNonCurrentLiabilities": 947252000,
    "otherLiabilities": 0,